pretty_midi_fluidsynth/TimGM6mb.sf2
pretty_midi_fluidsynth/__init__.py
pretty_midi_fluidsynth/constants.py
pretty_midi_fluidsynth/containers.py
pretty_midi_fluidsynth/fluidsynth.py
pretty_midi_fluidsynth/instrument.py
pretty_midi_fluidsynth/pretty_midi.py
pretty_midi_fluidsynth/utilities.py
pretty_midi_fluidsynth-0.1.1.dist-info/LICENSE.txt
pretty_midi_fluidsynth-0.1.1.dist-info/METADATA
pretty_midi_fluidsynth-0.1.1.dist-info/WHEEL
pretty_midi_fluidsynth-0.1.1.dist-info/top_level.txt
pretty_midi_fluidsynth-0.1.1.dist-info/RECORD
