Metadata-Version: 2.1
Name: pretty-midi-fluidsynth
Version: 0.1.1
Summary: Functions and classes for handling MIDI data conveniently.
Home-page: https://github.com/Mu-jun/pretty-midi
Author: Mu-jun
Author-email: suo24448@gmail.com
License: MIT
Keywords: audio music midi mir
Platform: UNKNOWN
Classifier: License :: OSI Approved :: MIT License
Classifier: Programming Language :: Python
Classifier: Development Status :: 3 - Alpha
Classifier: Intended Audience :: Developers
Classifier: Topic :: Multimedia :: Sound/Audio :: MIDI
License-File: LICENSE.txt
Requires-Dist: numpy (>=1.7.0)
Requires-Dist: mido (>=1.1.16)
Requires-Dist: six
